backports/httpmethod/__init__.py
backports/httpmethod/py.typed
backports_httpmethod-0.2.1.dist-info/METADATA
backports_httpmethod-0.2.1.dist-info/WHEEL
backports_httpmethod-0.2.1.dist-info/licenses/LICENSE
backports_httpmethod-0.2.1.dist-info/RECORD
