Metadata-Version: 2.3
Name: backports-httpmethod
Version: 0.2.1
Summary: A backport of Python 3.11+ `http.HTTPMethod` enum
Project-URL: Documentation, https://github.com/edgarrmondragon/backports.httpmethod#readme
Project-URL: Issues, https://github.com/edgarrmondragon/backports.httpmethod/issues
Project-URL: Source, https://github.com/edgarrmondragon/backports.httpmethod
Author-email: Edgar Ramírez-Mondragón <edgarrmondragon@hey.com>
Maintainer-email: Edgar Ramírez-Mondragón <edgarrmondragon@hey.com>
License: MIT License
License-File: LICENSE
Keywords: backports,enum,http,httpmethod
Classifier: Development Status :: 4 - Beta
Classifier: Programming Language :: Python
Classifier: Programming Language :: Python :: 3 :: Only
Classifier: Programming Language :: Python :: 3.7
Classifier: Programming Language :: Python :: 3.8
Classifier: Programming Language :: Python :: 3.9
Classifier: Programming Language :: Python :: 3.10
Classifier: Programming Language :: Python :: 3.11
Classifier: Programming Language :: Python :: 3.12
Classifier: Programming Language :: Python :: 3.13
Classifier: Programming Language :: Python :: 3.14
Classifier: Programming Language :: Python :: Implementation :: CPython
Classifier: Programming Language :: Python :: Implementation :: PyPy
Requires-Python: >=3.7
Requires-Dist: backports-strenum; python_version < '3.11'
